alice_host/__init__.py
alice_host/web_api.py
alice_host-0.0.7.dist-info/LICENSE
alice_host-0.0.7.dist-info/METADATA
alice_host-0.0.7.dist-info/WHEEL
alice_host-0.0.7.dist-info/top_level.txt
alice_host-0.0.7.dist-info/RECORD
