Metadata-Version: 2.1
Name: alice-host
Version: 0.0.7
Summary: Alice Host its come with ui page!
Home-page: https://github.com/alice-api/alice-host
Author: pipatpong
Author-email: kanyatit2500@email.com
License: MIT
Classifier: Programming Language :: Python :: 3
Classifier: Development Status :: 4 - Beta
Classifier: License :: OSI Approved :: MIT License
Classifier: Operating System :: OS Independent
License-File: LICENSE
Requires-Dist: templates
